CHANGES.txt
MANIFEST.in
README.txt
setup.py
twotest/__init__.py
twotest/emptyurls.py
twotest/fixtures.py
twotest/quicktest.py
twotest/util.py
twotest.egg-info/PKG-INFO
twotest.egg-info/SOURCES.txt
twotest.egg-info/dependency_links.txt
twotest.egg-info/namespace_packages.txt
twotest.egg-info/not-zip-safe
twotest.egg-info/requires.txt
twotest.egg-info/top_level.txt
twotest/management/__init__.py
twotest/management/commands/__init__.py
twotest/management/commands/ptest.py