Metadata-Version: 1.1
Name: twotest
Version: 0.9.1
Summary: It takes Two to Django. py.test support for Django
Home-page: http://github.com/iivvoo/two.test
Author: Ivo van der Wijk
Author-email: two@in.m3r.nl
License: BSD
Platform: UNKNOWN
Classifier: Programming Language :: Python
